my_lib/__init__.py
my_lib/app.py
mylib_namik-0.0.2.dist-info/METADATA
mylib_namik-0.0.2.dist-info/WHEEL
mylib_namik-0.0.2.dist-info/entry_points.txt
mylib_namik-0.0.2.dist-info/top_level.txt
mylib_namik-0.0.2.dist-info/RECORD
